[
    {
        "MaSP":1,
        "TenSP":"Áo hai dây hình học giải trí",
        "LoaiSP":"Áo",
        "Hang": "SHEIN",
        "Discount":20,
        "Price":150000,
        "Hinhanh":[ 
            "didu01/didu01_1.jpeg",
            "didu01/didu01_2.jpeg",
            "didu01/didu01_3.jpeg",
            "didu01/didu01_4.jpeg"
                    ],
        "Mota":[
        "Độ mới: 90%", 
        "Màu sắc: màu xanh",
        "Phong cách: Giải trí",
        "Kiểu mẫu: Hình học",
        "Sợi vải: Căng nhẹ",
        "Vật liệu: Polyester",
        "Thành phần: 95% Polyester, 5% Bông vải thun",
        "* Model: 1m67 - 46 kg", 
        "* *Lưu ý: Sản phẩm là hàng 2hand được Kho tuyển chọn kỹ càng, mỗi mẫu có số lượng có hạn nên Khách tham khảo số đo sản phẩm giúp kho nhé !"],
        "Soluong":5,
        "Size":"L"
    },
    {
        "MaSP":2,
        "TenSP":"Áo nữ Xù nhỏ cắt loại bướm giải trí",
        "LoaiSP":"Áo",
        "Hang": "ZARA",
        "Discount":0,
        "Price":80000,
        "Hinhanh": [
                "didu02/didu02_1.jpeg",
                "didu02/didu02_2.jpeg",
                "didu02/didu02_3.jpeg",
                "didu02/didu02_4.jpeg"
        ],
        "Mota":[
            "Độ mới: 90%", 
            "Màu sắc: màu xanh",
            "Phong cách: Giải trí",
            "Kiểu mẫu: Hình học",
            "Sợi vải: Căng nhẹ",
            "Vật liệu: Polyester",
            "Thành phần: 95% Polyester, 5% Bông vải thun",
            "* Model: 1m67 - 46 kg", 
            "* *Lưu ý: Sản phẩm là hàng 2hand được Kho tuyển chọn kỹ càng, mỗi mẫu có số lượng có hạn nên Khách tham khảo số đo sản phẩm giúp kho nhé !"],
        "Soluong":3,
        "Size":"Freesize"
        
    },
    {
        "MaSP":3,
        "TenSP":"Áo thun nữ màu trơn giải trí",
        "LoaiSP":"Áo",
        "Hang": "LABB",
        "Discount":0,
        "Price":120000,
        "Hinhanh": [
            "didu03/didu03_1.jpeg",
            "didu03/didu03_2.jpeg",
            "didu03/didu03_3.jpeg",
            "didu03/didu03_4.jpeg"
    ],
        "Mota":[
        "Độ mới: 90%", 
        "Màu sắc: màu nâu",
        "Phong cách: Giải trí",
        "Kiểu mẫu: Hình học",
        "Sợi vải: Căng nhẹ",
        "Vật liệu: Polyester",
        "Thành phần: 95% Polyester, 5% Bông vải thun",
        "* Model: 1m67 - 46 kg", 
        "* *Lưu ý: Sản phẩm là hàng 2hand được Kho tuyển chọn kỹ càng, mỗi mẫu có số lượng có hạn nên Khách tham khảo số đo sản phẩm giúp kho nhé !"],
        "Soluong":10,
        "Size":"Freesize"
    },
    {
        "MaSP":4,
        "TenSP":"Áo sơ mi chất rắn túi mặt trước nút thông qua thả vai",
        "LoaiSP":"Áo",
        "Hang": "H&M",
        "Discount":30,
        "Price":150000,
        "Hinhanh": [
            "didu04/didu04_1.jpeg",
            "didu04/didu04_2.jpeg",
            "didu04/didu04_3.jpeg",
            "didu04/didu04_4.jpeg"
    ],
        "Mota":[
        "Độ mới: 99%", 
        "Màu sắc: Màu xanh ",
        "Phong cách: Giải trí",
        "Kiểu mẫu: Hình học",
        "Sợi vải: Căng nhẹ",
        "Vật liệu: Polyester",
        "Thành phần: 95% Polyester, 5% Bông vải thun",
        "* Model: 1m67 - 46 kg", 
        "* *Lưu ý: Sản phẩm là hàng 2hand được Kho tuyển chọn kỹ càng, mỗi mẫu có số lượng có hạn nên Khách tham khảo số đo sản phẩm giúp kho nhé !"],
        "Soluong":10,
        "Size":"Freesize"
    },
    {
        "MaSP":5,
        "TenSP":" Đầm Thắt lưng khối màu thanh lịch",
        "LoaiSP":"Váy",
        "Hang": "JUNO",
        "Discount":10,
        "Price":250000,
        "Hinhanh": [
            "didu05/didu05_1.jpeg",
            "didu05/didu05_2.jpeg",
            "didu05/didu05_3.jpeg",
            "didu05/didu05_4.jpeg"
    ],
        "Mota":[
        "Độ mới: 98%", 
        "Màu sắc: màu be",
        "Phong cách: Gợi cảm",
        "Kiểu mẫu: màu trơn",
        "Sợi vải: Căng nhẹ",
        "Vật liệu: Polyester",
        "Thành phần: 95% Polyester, 5% Bông vải thun",
        "* Model: 1m67 - 46 kg", 
        "* *Lưu ý: Sản phẩm là hàng 2hand được Kho tuyển chọn kỹ càng, mỗi mẫu có số lượng có hạn nên Khách tham khảo số đo sản phẩm giúp kho nhé !"],
        "Soluong":2,
        "Size":"Freesize"
    },
    {
        "MaSP":6,
        "TenSP":"Đầm viền lá sen Nút phía trước Thực vật Tất cả trên in Boho",
        "LoaiSP":"Váy",
        "Hang": "ZARA",
        "Discount":0,
        "Price":190000,
        "Hinhanh": [
            "didu06/didu06_1.jpeg",
            "didu06/didu06_2.jpeg",
            "didu06/didu06_3.jpeg",
            "didu06/didu06_4.jpeg"
    ],
        "Mota":[
        "Độ mới: 92%", 
        "Màu sắc: Đen và trắng",
        "Phong cách: Giải trí",
        "Kiểu mẫu: Hình học",
        "Sợi vải: Căng nhẹ",
        "Vật liệu: Polyester",
        "Thành phần: 95% Polyester, 5% Bông vải thun",
        "* Model: 1m67 - 46 kg", 
        "* *Lưu ý: Sản phẩm là hàng 2hand được Kho tuyển chọn kỹ càng, mỗi mẫu có số lượng có hạn nên Khách tham khảo số đo sản phẩm giúp kho nhé !"],
        "Soluong":4,
        "Size":"S"
    },
    {
        "MaSP":7,
        "TenSP":"Váy nữ Tách cao màu trơn Giải trí",
        "LoaiSP":"Váy",
        "Hang": "H&M",
        "Discount":0,
        "Price":100000,
        "Hinhanh": [
            "didu07/didu07_1.jpeg",
            "didu07/didu07_2.jpeg",
            "didu07/didu07_3.jpeg",
            "didu07/didu07_4.jpeg"
    ],
        "Mota":[
        "Độ mới: 94%", 
        "Màu sắc: màu đen",
        "Phong cách: Giải trí",
        "Kiểu mẫu: Hình học",
        "Sợi vải: Căng nhẹ",
        "Vật liệu: Polyester",
        "Thành phần: 95% Polyester, 5% Bông vải thun",
        "* Model: 1m67 - 46 kg", 
        "* *Lưu ý: Sản phẩm là hàng 2hand được Kho tuyển chọn kỹ càng, mỗi mẫu có số lượng có hạn nên Khách tham khảo số đo sản phẩm giúp kho nhé !"],
        "Soluong":5,
        "Size":"Freesize"
    },
    {
        "MaSP":8,
        "TenSP":"Váy nữ Chia màu trơn Giải trí ",
        "LoaiSP":"Váy",
        "Hang": "ZARA",
        "Discount":0,
        "Price":90000,
        "Hinhanh": [
            "didu08/didu08_1.jpeg",
            "didu08/didu08_2.jpeg",
            "didu08/didu08_3.jpeg",
            "didu08/didu08_4.jpeg"
    ],
        "Mota":[
        "Độ mới: 90%", 
        "Màu sắc: màu đen",
        "Phong cách: Giải trí",
        "Kiểu mẫu: Hình học",
        "Sợi vải: Căng nhẹ",
        "Vật liệu: Polyester",
        "Thành phần: 95% Polyester, 5% Bông vải thun",
        "* Model: 1m67 - 46 kg", 
        "* *Lưu ý: Sản phẩm là hàng 2hand được Kho tuyển chọn kỹ càng, mỗi mẫu có số lượng có hạn nên Khách tham khảo số đo sản phẩm giúp kho nhé !"],
        "Soluong":1,
        "Size":"Freesize"
    },
    {
        "MaSP":9,
        "TenSP":"Quần ống loe Đường may Chi tiết",
        "LoaiSP":"Quần",
        "Hang": "H&M",
        "Discount":10,
        "Price":140000,
        "Hinhanh": [
            "didu09/didu09_1.jpeg",
            "didu09/didu09_2.jpeg",
            "didu09/didu09_3.jpeg",
            "didu09/didu09_4.jpeg"
    ],
        "Mota":[
        "Độ mới: 90%", 
        "Màu sắc: màu nâu",
        "Phong cách: Giải trí",
        "Kiểu mẫu: Hình học",
        "Sợi vải: Căng nhẹ",
        "Vật liệu: Polyester",
        "Thành phần: 95% Polyester, 5% Bông vải thun",
        "* Model: 1m67 - 46 kg", 
        "* *Lưu ý: Sản phẩm là hàng 2hand được Kho tuyển chọn kỹ càng, mỗi mẫu có số lượng có hạn nên Khách tham khảo số đo sản phẩm giúp kho nhé !"],
        "Soluong":3,
        "Size":"S"
    },
    {
        "MaSP":10,
        "TenSP":"Váy nữ Chia Họa tiết hoa Boho",
        "LoaiSP":"Váy",
        "Hang": "JUNO",
        "Discount":0,
        "Price":90000,
        "Hinhanh": [
            "didu10/didu10_1.jpeg",
            "didu10/didu10_2.jpeg",
            "didu10/didu10_3.jpeg",
            "didu10/didu10_4.jpeg"
    ],
        "Mota":[
        "Độ mới: 95%", 
        "Màu sắc: màu be",
        "Phong cách: Giải trí",
        "Kiểu mẫu: Hình học",
        "Sợi vải: Căng nhẹ",
        "Vật liệu: Polyester",
        "Thành phần: 95% Polyester, 5% Bông vải thun",
        "* Model: 1m67 - 46 kg", 
        "* *Lưu ý: Sản phẩm là hàng 2hand được Kho tuyển chọn kỹ càng, mỗi mẫu có số lượng có hạn nên Khách tham khảo số đo sản phẩm giúp kho nhé !"],
        "Soluong":6,
        "Size":"Freesize"
    },
    {
        "MaSP":11,
        "TenSP":"Kính râm ống kính màu khung vuông",
        "LoaiSP":"Phụ kiện",
        "Hang": "JUNO",
        "Discount":0,
        "Price":69000,
        "Hinhanh": [
            "didu11/didu11_1.jpeg",
            "didu11/didu11_2.jpeg",
            "didu11/didu11_3.jpeg",
            "didu11/didu11_4.jpeg"
    ],
        "Mota":[
        "Độ mới: 100%", 
        "Màu sắc: màu be",
        "* *Lưu ý: Sản phẩm là hàng 2hand được Kho tuyển chọn kỹ càng, mỗi mẫu có số lượng có hạn nên Khách tham khảo số đo sản phẩm giúp kho nhé !"],
        "Soluong":10,
        "Size":"Freesize"
    },
    {
        "MaSP":12,
        "TenSP":"Hoa trang trí tóc Claw",
        "LoaiSP":"Phụ kiện",
        "Hang": "JUNO",
        "Discount":0,
        "Price":45000,
        "Hinhanh": [
            "didu12/didu12_1.jpeg",
            "didu12/didu12_2.jpeg",
            "didu12/didu12_3.jpeg",
            "didu12/didu12_4.jpeg"
    ],
        "Mota":[
        "Độ mới: 100%", 
        "Màu sắc: màu xanh",
        "Phong cách: Giải trí"
        ],
        "Soluong":10,
        "Size":"Freesize"
    },
    {
        "MaSP":13,
        "TenSP":"Váy nữ Xù nhỏ Con số Chắp vá Thanh lịch",
        "LoaiSP":"Váy",
        "Hang": "SHEIN",
        "Discount":30,
        "Price":145000,
        "Hinhanh": [
            "didu13/didu13_1.jpeg",
            "didu13/didu13_2.jpeg",
            "didu13/didu13_3.jpeg",
            "didu13/didu13_4.jpeg"
    ],
        "Mota":[
            "Độ mới: 99%", 
            "Màu sắc: màu nâu",
            "Phong cách: Giải trí",
            "Kiểu mẫu: Hình học",
            "Sợi vải: Căng nhẹ",
            "Vật liệu: Polyester",
            "Thành phần: 95% Polyester, 5% Bông vải thun",
            "* Model: 1m67 - 46 kg", 
            "* *Lưu ý: Sản phẩm là hàng 2hand được Kho tuyển chọn kỹ càng, mỗi mẫu có số lượng có hạn nên Khách tham khảo số đo sản phẩm giúp kho nhé !"
        ],
        "Soluong":10,
        "Size":"Freesize"
    },
    {
        "MaSP":14,
        "TenSP":"Áo nữ Xù nhỏ Nút phía trước Con số Gợi cảm",
        "LoaiSP":"Áo",
        "Hang": "SHEIN",
        "Discount":10,
        "Price":115000,
        "Hinhanh": [
            "didu14/didu14_1.jpeg",
            "didu14/didu14_2.jpeg",
            "didu14/didu14_3.jpeg",
            "didu14/didu14_4.jpeg"
    ],
        "Mota":[
            "Độ mới: 99%", 
            "Màu sắc: màu nâu",
            "Phong cách: Giải trí",
            "Kiểu mẫu: Hình học",
            "Sợi vải: Căng nhẹ",
            "Vật liệu: Polyester",
            "Thành phần: 95% Polyester, 5% Bông vải thun",
            "* Model: 1m67 - 46 kg", 
            "* *Lưu ý: Sản phẩm là hàng 2hand được Kho tuyển chọn kỹ càng, mỗi mẫu có số lượng có hạn nên Khách tham khảo số đo sản phẩm giúp kho nhé !"
        ],
        "Soluong":10,
        "Size":"Freesize"
    },
    {
        "MaSP":15,
        "TenSP":"Kính thời trang khung vuông Rhinestone trang trí",
        "LoaiSP":"Phụ kiện",
        "Hang": "ZARA",
        "Discount":0,
        "Price":99000,
        "Hinhanh": [
            "didu15/didu15_1.jpeg",
            "didu15/didu15_2.jpeg",
            "didu15/didu15_3.jpeg",
            "didu15/didu15_4.jpeg"
    ],
        "Mota":[
            "Độ mới: 99%", 
            "Màu sắc: màu nâu",
            "CẢNH BÁO: Mắt kính thời trang. Không được đeo bên ngoài để bảo vệ mắt chống lại ánh sáng mặt trời mạnh. Không được thiết kế hoặc dự định sử dụng trong chơi của trẻ em"
        ],
        "Soluong":20,
        "Size":"Freesize"
    },
    {
        "MaSP":16,
        "TenSP":"Váy nữ Chia Gân đan màu trơn Thanh lịch",
        "LoaiSP":"Váy",
        "Hang": "ZARA",
        "Discount":0,
        "Price":99000,
        "Hinhanh": [
            "didu16/didu16_1.jpeg",
            "didu16/didu16_2.jpeg",
            "didu16/didu16_3.jpeg",
            "didu16/didu16_4.jpeg"
    ],
        "Mota":[
            "Độ mới: 92%", 
            "Màu sắc: màu nâu",
            "Phong cách: Giải trí",
            "Kiểu mẫu: Hình học",
            "Sợi vải: Căng nhẹ",
            "Vật liệu: Polyester",
            "Thành phần: 95% Polyester, 5% Bông vải thun",
            "* Model: 1m67 - 46 kg", 
            "* *Lưu ý: Sản phẩm là hàng 2hand được Kho tuyển chọn kỹ càng, mỗi mẫu có số lượng có hạn nên Khách tham khảo số đo sản phẩm giúp kho nhé !"
        ],
        "Soluong":5,
        "Size":"M"
    },
    {
        "MaSP":17,
        "TenSP":"Váy nữ Dây kéo Xù màu trơn Giải trí",
        "LoaiSP":"Váy",
        "Hang": "SHEIN",
        "Discount":30,
        "Price":180000,
        "Hinhanh": [
            "didu17/didu17_1.jpeg",
            "didu17/didu17_2.jpeg",
            "didu17/didu17_3.jpeg",
            "didu17/didu17_4.jpeg"
    ],
        "Mota":[
            "Độ mới: 98%", 
            "Màu sắc: màu nâu",
            "Phong cách: Giải trí",
            "Kiểu mẫu: Hình học",
            "Sợi vải: Căng nhẹ",
            "Vật liệu: Polyester",
            "Thành phần: 95% Polyester, 5% Bông vải thun",
            "* Model: 1m67 - 46 kg", 
            "* *Lưu ý: Sản phẩm là hàng 2hand được Kho tuyển chọn kỹ càng, mỗi mẫu có số lượng có hạn nên Khách tham khảo số đo sản phẩm giúp kho nhé !"
        ],
        "Soluong":10,
        "Size":"Freesize"
    },
    {
        "MaSP":18,
        "TenSP":"Váy nữ màu trơn Giải trí",
        "LoaiSP":"Váy",
        "Hang": "SHEIN",
        "Discount":20,
        "Price":200000,
        "Hinhanh": [
            "didu18/didu18_1.jpeg",
            "didu18/didu18_2.jpeg",
            "didu18/didu18_3.jpeg",
            "didu18/didu18_4.jpeg"
    ],
        "Mota":[
            "Độ mới: 95%", 
            "Màu sắc: màu nâu",
            "Phong cách: Giải trí",
            "Kiểu mẫu: Hình học",
            "Sợi vải: Căng nhẹ",
            "Vật liệu: Polyester",
            "Thành phần: 95% Polyester, 5% Bông vải thun",
            "* Model: 1m67 - 46 kg", 
            "* *Lưu ý: Sản phẩm là hàng 2hand được Kho tuyển chọn kỹ càng, mỗi mẫu có số lượng có hạn nên Khách tham khảo số đo sản phẩm giúp kho nhé !"
        ],
        "Soluong":10,
        "Size":"Freesize"
    },
    {
        "MaSP":19,
        "TenSP":"Váy nữ Sọc ca rô Sẵn sàng",
        "LoaiSP":"Váy",
        "Hang": "ZARA",
        "Discount":0,
        "Price":210000,
        "Hinhanh": [
            "didu19/didu19_1.jpeg",
            "didu19/didu19_2.jpeg",
            "didu19/didu19_3.jpeg",
            "didu19/didu19_4.jpeg"
    ],
        "Mota":[
            "Độ mới: 99%", 
            "Màu sắc: màu nâu",
            "Phong cách: Giải trí",
            "Kiểu mẫu: Hình học",
            "Sợi vải: Căng nhẹ",
            "Vật liệu: Polyester",
            "Thành phần: 95% Polyester, 5% Bông vải thun",
            "* Model: 1m67 - 46 kg", 
            "* *Lưu ý: Sản phẩm là hàng 2hand được Kho tuyển chọn kỹ càng, mỗi mẫu có số lượng có hạn nên Khách tham khảo số đo sản phẩm giúp kho nhé !"
        ],
        "Soluong":1,
        "Size":"S"
    },
    {
        "MaSP":20,
        "TenSP":"Quần nữ Túi Uốn nếp màu trơn",
        "LoaiSP":"Quần",
        "Hang": "SHEIN",
        "Discount":10,
        "Price":270000,
        "Hinhanh": [
            "didu20/didu20_1.jpeg",
            "didu20/didu20_2.jpeg",
            "didu20/didu20_3.jpeg",
            "didu20/didu20_4.jpeg"
    ],
        "Mota":[
            "Độ mới: 92%", 
            "Màu sắc: màu nâu",
            "Phong cách: Giải trí",
            "Kiểu mẫu: Hình học",
            "Sợi vải: Căng nhẹ",
            "Vật liệu: Polyester",
            "Thành phần: 95% Polyester, 5% Bông vải thun",
            "* Model: 1m67 - 46 kg", 
            "* *Lưu ý: Sản phẩm là hàng 2hand được Kho tuyển chọn kỹ càng, mỗi mẫu có số lượng có hạn nên Khách tham khảo số đo sản phẩm giúp kho nhé !"
        ],
        "Soluong":1,
        "Size":"M"
    },
    {
        "MaSP":21,
        "TenSP":"Vòng tay Đúng mốt",
        "LoaiSP":"Phụ kiện",
        "Hang": "SHEIN",
        "Discount":0,
        "Price":50000,
        "Hinhanh": [
            "didu21/didu21_1.jpeg",
            "didu21/didu21_2.jpeg",
            "didu21/didu21_3.jpeg",
            "didu21/didu21_4.jpeg"
    ],
        "Mota":[
            "Độ mới: 100%", 
            "Màu sắc: màu vàng",
            "Phong cách: Giải trí"
        ],
        "Soluong":20,
        "Size":"Freesize"
    },
    {
        "MaSP":22,
        "TenSP":"Vòng tay trang trí bằng bóng ",
        "LoaiSP":"Phụ kiện",
        "Hang": "JUNO",
        "Discount":0,
        "Price":45000,
        "Hinhanh": [
            "didu22/didu22_1.jpeg",
            "didu22/didu22_2.jpeg",
            "didu22/didu22_3.jpeg",
            "didu22/didu22_4.jpeg"
    ],
        "Mota":[
            "Độ mới: 100%", 
            "Màu sắc: màu nâu",
            "Phong cách: Giải trí"
        ],
        "Soluong":19,
        "Size":"Freesize"
    },
    {
        "MaSP":23,
        "TenSP":"Áo hai dây Nút phía trước Sọc ca rô Giải trí",
        "LoaiSP":"Áo",
        "Hang": "SHEIN",
        "Discount":20,
        "Price":210000,
        "Hinhanh": [
            "didu23/didu23_1.jpeg",
            "didu23/didu23_2.jpeg",
            "didu23/didu23_3.jpeg",
            "didu23/didu23_4.jpeg"
    ],
        "Mota":[
            "Độ mới: 95%", 
            "Màu sắc: màu nâu",
            "Phong cách: Giải trí",
            "Kiểu mẫu: Hình học",
            "Sợi vải: Căng nhẹ",
            "Vật liệu: Polyester",
            "Thành phần: 95% Polyester, 5% Bông vải thun",
            "* Model: 1m67 - 46 kg", 
            "* *Lưu ý: Sản phẩm là hàng 2hand được Kho tuyển chọn kỹ càng, mỗi mẫu có số lượng có hạn nên Khách tham khảo số đo sản phẩm giúp kho nhé !"
        ],
        "Soluong":1,
        "Size":"S"
    },
    {
        "MaSP":24,
        "TenSP":"MOD Áo thun nữ Gân đan màu trơn Giải trí",
        "LoaiSP":"Áo",
        "Hang": "JUNO",
        "Discount":0,
        "Price":120000,
        "Hinhanh": [
            "didu24/didu24_1.jpeg",
            "didu24/didu24_2.jpeg",
            "didu24/didu24_3.jpeg",
            "didu24/didu24_4.jpeg"
    ],
        "Mota":[
            "Độ mới: 95%", 
            "Màu sắc: màu đen",
            "Phong cách: Giải trí",
            "Kiểu mẫu: Hình học",
            "Sợi vải: Căng nhẹ",
            "Vật liệu: Polyester",
            "Thành phần: 95% Polyester, 5% Bông vải thun",
            "* Model: 1m67 - 46 kg", 
            "* *Lưu ý: Sản phẩm là hàng 2hand được Kho tuyển chọn kỹ càng, mỗi mẫu có số lượng có hạn nên Khách tham khảo số đo sản phẩm giúp kho nhé !"
        ],
        "Soluong":1,
        "Size":"M"
    },
    {
        "MaSP":25,
        "TenSP":"DAZY Áo thun nữ màu trơn Giải trí",
        "LoaiSP":"Áo",
        "Hang": "SHEIN",
        "Discount":0,
        "Price":99000,
        "Hinhanh": [
            "didu25/didu25_1.jpeg",
            "didu25/didu25_2.jpeg",
            "didu25/didu25_3.jpeg",
            "didu25/didu25_4.jpeg"
    ],
        "Mota":[
            "Độ mới: 92%", 
            "Màu sắc: màu be",
            "Phong cách: Giải trí",
            "Kiểu mẫu: Hình học",
            "Sợi vải: Căng nhẹ",
            "Vật liệu: Polyester",
            "Thành phần: 95% Polyester, 5% Bông vải thun",
            "* Model: 1m67 - 46 kg", 
            "* *Lưu ý: Sản phẩm là hàng 2hand được Kho tuyển chọn kỹ càng, mỗi mẫu có số lượng có hạn nên Khách tham khảo số đo sản phẩm giúp kho nhé !"
        ],
        "Soluong":10,
        "Size":"Freesize"
    }
    

]